LearningHardCBokeYuanwenFix1/README.md
LearningHardCBokeYuanwenFix1/__init__.py
LearningHardCBokeYuanwenFix1/__main__.py
LearningHardCBokeYuanwenFix1/file.epub
LearningHardCBokeYuanwenFix1/index.html
LearningHardCBokeYuanwenFix1/css/__init__.py
LearningHardCBokeYuanwenFix1/css/annotations.css
LearningHardCBokeYuanwenFix1/css/main.css
LearningHardCBokeYuanwenFix1/css/normalize.css
LearningHardCBokeYuanwenFix1/css/popup.css
LearningHardCBokeYuanwenFix1/font/__init__.py
LearningHardCBokeYuanwenFix1/font/fontello.eot
LearningHardCBokeYuanwenFix1/font/fontello.svg
LearningHardCBokeYuanwenFix1/font/fontello.ttf
LearningHardCBokeYuanwenFix1/font/fontello.woff
LearningHardCBokeYuanwenFix1/img/__init__.py
LearningHardCBokeYuanwenFix1/img/annotator-glyph-sprite.png
LearningHardCBokeYuanwenFix1/img/annotator-icon-sprite.png
LearningHardCBokeYuanwenFix1/img/apple-touch-icon.png
LearningHardCBokeYuanwenFix1/img/cancelfullscreen.png
LearningHardCBokeYuanwenFix1/img/close.png
LearningHardCBokeYuanwenFix1/img/fullscreen.png
LearningHardCBokeYuanwenFix1/img/loader.gif
LearningHardCBokeYuanwenFix1/img/menu-icon.png
LearningHardCBokeYuanwenFix1/img/save.png
LearningHardCBokeYuanwenFix1/img/saved.png
LearningHardCBokeYuanwenFix1/img/settings-s.png
LearningHardCBokeYuanwenFix1/img/settings.png
LearningHardCBokeYuanwenFix1/img/star.png
LearningHardCBokeYuanwenFix1/js/__init__.py
LearningHardCBokeYuanwenFix1/js/epub.js
LearningHardCBokeYuanwenFix1/js/epub.min.js
LearningHardCBokeYuanwenFix1/js/epub.min.map
LearningHardCBokeYuanwenFix1/js/hooks.min.js
LearningHardCBokeYuanwenFix1/js/hooks.min.map
LearningHardCBokeYuanwenFix1/js/reader.js
LearningHardCBokeYuanwenFix1/js/reader.js.map
LearningHardCBokeYuanwenFix1/js/reader.min.js
LearningHardCBokeYuanwenFix1/js/reader.min.map
LearningHardCBokeYuanwenFix1/js/hooks/__init__.py
LearningHardCBokeYuanwenFix1/js/hooks/extensions/__init__.py
LearningHardCBokeYuanwenFix1/js/hooks/extensions/highlight.js
learning_hard_c_boke_yuanwen_fix1-2024.3.1.0.dist-info/METADATA
learning_hard_c_boke_yuanwen_fix1-2024.3.1.0.dist-info/WHEEL
learning_hard_c_boke_yuanwen_fix1-2024.3.1.0.dist-info/entry_points.txt
learning_hard_c_boke_yuanwen_fix1-2024.3.1.0.dist-info/top_level.txt
learning_hard_c_boke_yuanwen_fix1-2024.3.1.0.dist-info/RECORD
